{
  "generated_at": "2026-07-16T16:50:52+00:00",
  "status": "ok",
  "providers": {
    "binance_plugin": false,
    "binance_public_api": false,
    "coingecko_public_api": true,
    "alternative_fear_greed": true
  },
  "market": {
    "sentiment": "extreme_fear",
    "average_change_percent_24h": -0.98,
    "tracked_quote_volume_24h": 43762712745.0,
    "signal_strength": 4
  },
  "fear_greed": {
    "value": 25,
    "label": "Extreme Fear",
    "source": "alternative.me",
    "timestamp": "1784160000"
  },
  "tickers": [
    {
      "symbol": "BTCUSDT",
      "keyword": "bitcoin",
      "last_price": 64389.0,
      "price_change_percent_24h": -0.95558,
      "quote_volume_24h": 29121238774.0,
      "trade_count_24h": 0,
      "provider": "coingecko_public_api"
    },
    {
      "symbol": "ETHUSDT",
      "keyword": "ethereum",
      "last_price": 1875.68,
      "price_change_percent_24h": -2.05471,
      "quote_volume_24h": 10900628922.0,
      "trade_count_24h": 0,
      "provider": "coingecko_public_api"
    },
    {
      "symbol": "SOLUSDT",
      "keyword": "crypto_etf",
      "last_price": 76.12,
      "price_change_percent_24h": -1.74792,
      "quote_volume_24h": 1714426894.0,
      "trade_count_24h": 0,
      "provider": "coingecko_public_api"
    },
    {
      "symbol": "XRPUSDT",
      "keyword": "crypto_etf",
      "last_price": 1.11,
      "price_change_percent_24h": -0.36571,
      "quote_volume_24h": 1028601401.0,
      "trade_count_24h": 0,
      "provider": "coingecko_public_api"
    },
    {
      "symbol": "BNBUSDT",
      "keyword": "crypto_etf",
      "last_price": 576.88,
      "price_change_percent_24h": -0.18152,
      "quote_volume_24h": 551397615.0,
      "trade_count_24h": 0,
      "provider": "coingecko_public_api"
    },
    {
      "symbol": "DOGEUSDT",
      "keyword": "crypto_etf",
      "last_price": 0.073347,
      "price_change_percent_24h": -0.58103,
      "quote_volume_24h": 446419139.0,
      "trade_count_24h": 0,
      "provider": "coingecko_public_api"
    }
  ],
  "plugin_overview": {
    "available": false,
    "provider": "binance_plugin",
    "market_cap": {},
    "volume": {},
    "fear_greed": {
      "value": null,
      "label": ""
    },
    "hot_tokens": [],
    "news": []
  },
  "keyword_signals": {
    "bitcoin": {
      "signal_score_bonus": 3,
      "market_signal_notes": [
        "Fear/Greed 25: Extreme Fear zone"
      ],
      "tracked_symbols": [
        "BTCUSDT"
      ],
      "market_sentiment": "extreme_fear"
    },
    "ethereum": {
      "signal_score_bonus": 5,
      "market_signal_notes": [
        "ETHUSDT 24h change -2.05%",
        "Fear/Greed 25: Extreme Fear zone"
      ],
      "tracked_symbols": [
        "ETHUSDT"
      ],
      "market_sentiment": "extreme_fear"
    },
    "crypto_etf": {
      "signal_score_bonus": 6,
      "market_signal_notes": [
        "Fear/Greed 25: Extreme Fear zone"
      ],
      "tracked_symbols": [
        "SOLUSDT",
        "XRPUSDT",
        "BNBUSDT",
        "DOGEUSDT"
      ],
      "market_sentiment": "extreme_fear"
    }
  }
}